bruces/VERSION
bruces/__init__.py
bruces/_catalog.py
bruces/_common.py
bruces/_earthquake.py
bruces/_helpers.py
bruces/_io/__init__.py
bruces/_io/_helpers.py
bruces/_io/csv/__init__.py
bruces/_io/csv/_read.py
bruces/_io/csv/_write.py
bruces/decluster/__init__.py
bruces/decluster/_helpers.py
bruces/decluster/gardner_knopoff/__init__.py
bruces/decluster/gardner_knopoff/_gardner_knopoff.py
bruces/decluster/nearest_neighbor/__init__.py
bruces/decluster/nearest_neighbor/_nearest_neighbor.py
bruces/decluster/reasenberg/__init__.py
bruces/decluster/reasenberg/_reasenberg.py
bruces/modeling/__init__.py
bruces/modeling/_etas.py
bruces/modeling/_magnitude_time.py
bruces/modeling/_seismicity_rate.py
bruces/modeling/_seismogram.py
bruces/stats/__init__.py
bruces/stats/_poisson_process.py
bruces/stats/_sample_magnitude.py
bruces/utils/__init__.py
bruces/utils/_datetime.py
bruces-0.5.0.dist-info/LICENSE
bruces-0.5.0.dist-info/METADATA
bruces-0.5.0.dist-info/WHEEL
bruces-0.5.0.dist-info/top_level.txt
bruces-0.5.0.dist-info/RECORD
