Metadata-Version: 2.1
Name: bruces
Version: 0.5.0
Summary: A bunch of really useful codes for earthquake stuff
Home-page: https://github.com/keurfonluu/bruces
Author: Keurfon Luu
License: BSD 3-Clause License
Project-URL: Code, https://github.com/keurfonluu/bruces
Project-URL: Issues, https://github.com/keurfonluu/bruces/issues
Platform: any
Classifier: License :: OSI Approved :: BSD License
Classifier: Operating System :: OS Independent
Classifier: Development Status :: 4 - Beta
Classifier: Programming Language :: Python :: 3.7
Classifier: Programming Language :: Python :: 3.8
Classifier: Programming Language :: Python :: 3.9
Classifier: Programming Language :: Python :: 3.10
Classifier: Natural Language :: English
Classifier: Intended Audience :: Science/Research
Classifier: Topic :: Scientific/Engineering
Requires-Python: >=3.7
License-File: LICENSE
Requires-Dist: importlib-metadata
Requires-Dist: numpy
Requires-Dist: scipy
Requires-Dist: numba
Requires-Dist: matplotlib
Requires-Dist: utm
Provides-Extra: full
Requires-Dist: disba ; extra == 'full'
Requires-Dist: scikit-learn ; extra == 'full'
